setup.py
coderwall/__init__.py
coderwall/main.py
pycoderwall.egg-info/PKG-INFO
pycoderwall.egg-info/SOURCES.txt
pycoderwall.egg-info/dependency_links.txt
pycoderwall.egg-info/entry_points.txt
pycoderwall.egg-info/requires.txt
pycoderwall.egg-info/top_level.txt